pyiapws/__init__.py
pyiapws/_iapws.cpython-312-darwin.so
pyiapws/libiapws.a
pyiapws/libiapws.dylib
pyiapws-0.5.0.dist-info/licenses/LICENSE
pyiapws-0.5.0.dist-info/METADATA
pyiapws-0.5.0.dist-info/WHEEL
pyiapws-0.5.0.dist-info/top_level.txt
pyiapws-0.5.0.dist-info/RECORD
