Metadata-Version: 2.4
Name: pyiapws
Version: 0.5.0
Summary: pyiapws: IAPWS for python.
Author-email: Milan Skocic <milan.skocic@gmail.com>
License-Expression: MIT
Project-URL: Documentation, https://milanskocic.github.io/iapws/index.html
Project-URL: Source, https://github.com/MilanSkocic/iapws
Classifier: Development Status :: 5 - Production/Stable
Classifier: Intended Audience :: Science/Research
Requires-Python: >=3.10
License-File: LICENSE
Requires-Dist: numpy>=1.23
Provides-Extra: test
Requires-Dist: pytest; extra == "test"
Dynamic: license-file
